[
  {
    "id": 1,
    "first_name": "Armin",
    "last_name": "Arlelt",
    "species": "Human, Intelligent Titan",
    "age": 19,
    "height": 60,
    "residence": "Wall Rose",
    "status": "Alive",
    "alias": "Colossal Titan"
  },
  {
    "id": 2,
    "first_name": "Mikasa",
    "last_name": "Ackermann",
    "species": "Human",
    "age": 19,
    "height": null,
    "residence": "Wall Rose",
    "status": "Alive",
    "alias": null
  },
  {
    "id": 3,
    "first_name": "Hange",
    "last_name": "Zoë",
    "species": "Human",
    "age": null,
    "height": null,
    "residence": "Wall Rose",
    "status": "Alive",
    "alias": null
  },
  {
    "id": 4,
    "first_name": "Jean",
    "last_name": "Kirschtein",
    "species": "Human",
    "age": 19,
    "height": null,
    "residence": " Wall Rose",
    "status": "Alive",
    "alias": "Horse face, Jean-boy"
  },
  {
    "id": 5,
    "first_name": "Conny",
    "last_name": "Springer",
    "species": "Human",
    "age": 19,
    "height": null,
    "residence": "Wall Rose",
    "status": "Alive",
    "alias": null
  },
  {
    "id": 6,
    "first_name": "Daz",
    "last_name": null,
    "species": "Human",
    "age": null,
    "height": null,
    "residence": "Wall Rose",
    "status": "Alive",
    "alias": null
  },
  {
    "id": 7,
    "first_name": "Buchwald",
    "last_name": null,
    "species": "Horse",
    "age": null,
    "height": null,
    "residence": "Wall Rose",
    "status": "Alive",
    "alias": null
  },
  {
    "id": 8,
    "first_name": "Levi",
    "last_name": "Ackermann",
    "species": "Human",
    "age": 30,
    "height": null,
    "residence": "Wall Rose",
    "status": "Alive",
    "alias": "Humanity's Strongest Soldier"
  },
  {
    "id": 9,
    "first_name": "Lima",
    "last_name": null,
    "species": "Human",
    "age": null,
    "height": null,
    "residence": null,
    "status": "Unknown",
    "alias": null
  },
  {
    "id": 10,
    "first_name": "Charrette",
    "last_name": null,
    "species": "Horse",
    "age": null,
    "height": null,
    "residence": "Wall Rose",
    "status": "Unknown",
    "alias": null
  },
  {
    "id": 11,
    "first_name": "Varis",
    "last_name": null,
    "species": "Titan (formerly human)",
    "age": null,
    "height": null,
    "residence": null,
    "status": null,
    "alias": null
  },
  {
    "id": 12,
    "first_name": "Sasha",
    "last_name": "Braus",
    "species": null,
    "age": null,
    "height": 20,
    "residence": "Wall Rose",
    "status": "Deceased",
    "alias": "Potato Girl"
  },
  {
    "id": 13,
    "first_name": "Lobov",
    "last_name": null,
    "species": "Male",
    "age": null,
    "height": null,
    "residence": null,
    "status": "Deceased",
    "alias": null
  },
  {
    "id": 14,
    "first_name": "Erwin",
    "last_name": "Smith",
    "species": "Human",
    "age": null,
    "height": null,
    "residence": "Wall Rose",
    "status": "Deceased",
    "alias": "Eyebrow"
  },
  {
    "id": 15,
    "first_name": "Sandra",
    "last_name": null,
    "species": "Human",
    "age": null,
    "height": null,
    "residence": "Wall Rose",
    "status": "Deceased",
    "alias": null
  },
  {
    "id": 16,
    "first_name": "Gordon",
    "last_name": null,
    "species": "Human",
    "age": null,
    "height": null,
    "residence": "Wall Rose",
    "status": "Deceased",
    "alias": null
  },
  {
    "id": 17,
    "first_name": "Marlo",
    "last_name": "Freudenberg",
    "species": "Human",
    "age": null,
    "height": null,
    "residence": "Wall Sina",
    "status": "Deceased",
    "alias": null
  },
  {
    "id": 18,
    "first_name": "Tomas",
    "last_name": null,
    "species": "Human",
    "age": null,
    "height": null,
    "residence": "Wall Rose",
    "status": "Deceased",
    "alias": null
  },
  {
    "id": 19,
    "first_name": "Dieter",
    "last_name": null,
    "species": "Human",
    "age": null,
    "height": null,
    "residence": "Wall Rose",
    "status": "Deceased",
    "alias": null
  },
  {
    "id": 20,
    "first_name": "Dirk",
    "last_name": null,
    "species": "Human",
    "age": null,
    "height": null,
    "residence": "Wall Rose",
    "status": "Deceased",
    "alias": null
  },
  {
    "id": 21,
    "first_name": "Marlene",
    "last_name": null,
    "species": "Human",
    "age": null,
    "height": null,
    "residence": "Wall Rose",
    "status": "Deceased",
    "alias": null
  },
  {
    "id": 22,
    "first_name": "Klaus",
    "last_name": null,
    "species": "Human",
    "age": null,
    "height": null,
    "residence": "Wall Rose",
    "status": "Deceased",
    "alias": null
  },
  {
    "id": 23,
    "first_name": "Harold",
    "last_name": null,
    "species": "Human",
    "age": null,
    "height": null,
    "residence": "Wall Rose",
    "status": "Deceased",
    "alias": null
  },
  {
    "id": 24,
    "first_name": "Rashad",
    "last_name": null,
    "species": "Human",
    "age": null,
    "height": null,
    "residence": "Wall Rose",
    "status": "Deceased",
    "alias": null
  },
  {
    "id": 25,
    "first_name": "Lauda",
    "last_name": null,
    "species": "Human",
    "age": null,
    "height": null,
    "residence": "Wall Rose",
    "status": "Deceased",
    "alias": null
  },
  {
    "id": 26,
    "first_name": "Moblit",
    "last_name": "Berner",
    "species": "Human",
    "age": null,
    "height": null,
    "residence": "Wall Rose",
    "status": "Deceased",
    "alias": null
  },
  {
    "id": 27,
    "first_name": "Keiji",
    "last_name": null,
    "species": "Human",
    "age": null,
    "height": null,
    "residence": "Wall Rose",
    "status": "Deceased",
    "alias": null
  },
  {
    "id": 28,
    "first_name": "Abel",
    "last_name": null,
    "species": "Human",
    "age": null,
    "height": null,
    "residence": "Wall Rose",
    "status": "Deceased",
    "alias": "Goggles"
  },
  {
    "id": 29,
    "first_name": "Nifa",
    "last_name": null,
    "species": "Human",
    "age": null,
    "height": null,
    "residence": "Wall Rose",
    "status": "Deceased",
    "alias": null
  },
  {
    "id": 30,
    "first_name": "Peer",
    "last_name": null,
    "species": "Human",
    "age": null,
    "height": null,
    "residence": "Wall Rose",
    "status": "Deceased",
    "alias": null
  },
  {
    "id": 31,
    "first_name": "Nanaba",
    "last_name": null,
    "species": "Human",
    "age": null,
    "height": null,
    "residence": "Wall Rose",
    "status": "Deceased",
    "alias": null
  },
  {
    "id": 32,
    "first_name": "Gelgar",
    "last_name": null,
    "species": "Human",
    "age": null,
    "height": null,
    "residence": "Wall Rose",
    "status": "Deceased",
    "alias": null
  },
  {
    "id": 33,
    "first_name": "Henning",
    "last_name": null,
    "species": "Human",
    "age": null,
    "height": null,
    "residence": "Wall Rose",
    "status": "Deceased",
    "alias": null
  },
  {
    "id": 34,
    "first_name": "Lynne",
    "last_name": null,
    "species": "Human",
    "age": null,
    "height": null,
    "residence": "Wall Rose",
    "status": "Deceased",
    "alias": null
  },
  {
    "id": 35,
    "first_name": "Miche",
    "last_name": "Zacharius",
    "species": "Human",
    "age": null,
    "height": null,
    "residence": "Wall Rose",
    "status": "Deceased",
    "alias": null
  },
  {
    "id": 36,
    "first_name": "Jurgen",
    "last_name": null,
    "species": "Human",
    "age": null,
    "height": null,
    "residence": "Wall Rose",
    "status": "Deceased",
    "alias": null
  },
  {
    "id": 37,
    "first_name": "Ivan",
    "last_name": null,
    "species": "Human",
    "age": null,
    "height": null,
    "residence": "Wall Rose",
    "status": "Deceased",
    "alias": null
  },
  {
    "id": 38,
    "first_name": "Oruo",
    "last_name": "Bozad",
    "species": "Human",
    "age": null,
    "height": null,
    "residence": "Wall Rose",
    "status": "Deceased",
    "alias": null
  },
  {
    "id": 39,
    "first_name": "Petra",
    "last_name": "Rall",
    "species": "Human",
    "age": null,
    "height": null,
    "residence": "Wall Rose",
    "status": "Deceased",
    "alias": null
  },
  {
    "id": 40,
    "first_name": "Eld",
    "last_name": "Gin",
    "species": "Human",
    "age": null,
    "height": null,
    "residence": "Wall Rose",
    "status": "Deceased",
    "alias": null
  },
  {
    "id": 41,
    "first_name": "Gunther",
    "last_name": "Schultz",
    "species": "Human",
    "age": null,
    "height": null,
    "residence": "Wall Rose",
    "status": "Deceased",
    "alias": null
  },
  {
    "id": 42,
    "first_name": "Darius",
    "last_name": "Walbrunn",
    "species": "Human",
    "age": null,
    "height": null,
    "residence": "Wall Rose",
    "status": "Deceased",
    "alias": null
  },
  {
    "id": 43,
    "first_name": "Dieter",
    "last_name": "Ness",
    "species": "Human",
    "age": null,
    "height": null,
    "residence": "Wall Rose",
    "status": "Deceased",
    "alias": null
  },
  {
    "id": 44,
    "first_name": "Luke",
    "last_name": "Cis",
    "species": "Human",
    "age": null,
    "height": null,
    "residence": "Wall Rose",
    "status": "Deceased",
    "alias": null
  },
  {
    "id": 45,
    "first_name": "Ilse",
    "last_name": "Langnar",
    "species": "Human",
    "age": null,
    "height": null,
    "residence": "Wall Rose",
    "status": "Deceased",
    "alias": null
  },
  {
    "id": 46,
    "first_name": "Moses",
    "last_name": null,
    "species": "Human",
    "age": null,
    "height": null,
    "residence": "Wall Maria",
    "status": "Deceased",
    "alias": null
  },
  {
    "id": 47,
    "first_name": "Furlan",
    "last_name": "Church",
    "species": "Human",
    "age": null,
    "height": null,
    "residence": "Wall Maria",
    "status": "Deceased",
    "alias": null
  },
  {
    "id": 48,
    "first_name": "Flagon",
    "last_name": null,
    "species": "Human",
    "age": null,
    "height": null,
    "residence": "Wall Maria",
    "status": "Deceased",
    "alias": null
  },
  {
    "id": 49,
    "first_name": "Isabel",
    "last_name": "Magnolia",
    "species": "Human",
    "age": null,
    "height": null,
    "residence": "Wall Maria",
    "status": "Deceased",
    "alias": null
  },
  {
    "id": 50,
    "first_name": "Waltz",
    "last_name": null,
    "species": "Human",
    "age": null,
    "height": null,
    "residence": "Wall Sina",
    "status": "Alive",
    "alias": "Nile's aide, Aide soldie'"
  },
  {
    "id": 51,
    "first_name": "Nile",
    "last_name": "Dawk",
    "species": "Human",
    "age": null,
    "height": null,
    "residence": "Wall Rose",
    "status": "Alive",
    "alias": null
  },
  {
    "id": 52,
    "first_name": "Hitch",
    "last_name": "Dreyse",
    "species": "Human",
    "age": null,
    "height": null,
    "residence": "Wall Sina",
    "status": "Alive",
    "alias": null
  },
  {
    "id": 53,
    "first_name": "Boris",
    "last_name": "Feulner",
    "species": "Human",
    "age": null,
    "height": null,
    "residence": "Wall Sina",
    "status": "Alive",
    "alias": null
  },
  {
    "id": 54,
    "first_name": "Dennis",
    "last_name": "Aiblinger",
    "species": "Human",
    "age": null,
    "height": null,
    "residence": "Wall Sina",
    "status": "Alive",
    "alias": "Marlo's officer"
  },
  {
    "id": 55,
    "first_name": "Roger",
    "last_name": null,
    "species": "Human",
    "age": null,
    "height": null,
    "residence": "Wall Sina",
    "status": "Alive",
    "alias": null
  },
  {
    "id": 56,
    "first_name": "Roeg",
    "last_name": null,
    "species": "Human",
    "age": null,
    "height": null,
    "residence": null,
    "status": "Alive",
    "alias": null
  },
  {
    "id": 57,
    "first_name": "Kenny",
    "last_name": "Ackermann",
    "species": "Human",
    "age": null,
    "height": null,
    "residence": "Wall Sina",
    "status": "Deceased",
    "alias": "Kenny the Ripper"
  },
  {
    "id": 58,
    "first_name": "Caven",
    "last_name": null,
    "species": "Human",
    "age": null,
    "height": null,
    "residence": "Wall Sina",
    "status": "Deceased",
    "alias": null
  },
  {
    "id": 59,
    "first_name": "Duran",
    "last_name": null,
    "species": "Human",
    "age": null,
    "height": null,
    "residence": "Wall Sina",
    "status": "Deceased",
    "alias": null
  },
  {
    "id": 60,
    "first_name": "Dot",
    "last_name": "Pyxis",
    "species": "Human",
    "age": null,
    "height": null,
    "residence": "Wall Rose",
    "status": "Alive",
    "alias": null
  },
  {
    "id": 61,
    "first_name": "Gustav",
    "last_name": null,
    "species": "Human",
    "age": null,
    "height": null,
    "residence": "Wall Rose",
    "status": "Alive",
    "alias": null
  },
  {
    "id": 62,
    "first_name": "Anka",
    "last_name": "Rheinberger",
    "species": "Human",
    "age": null,
    "height": null,
    "residence": "Wall Rose",
    "status": "Alive",
    "alias": null
  },
  {
    "id": 63,
    "first_name": "Kitz",
    "last_name": "Woermann",
    "species": "Human",
    "age": null,
    "height": null,
    "residence": "Wall Rose",
    "status": "Alive",
    "alias": null
  },
  {
    "id": 64,
    "first_name": "Rico",
    "last_name": "Brzenska",
    "species": "Human",
    "age": null,
    "height": null,
    "residence": "Wall Rose",
    "status": "Alive",
    "alias": null
  },
  {
    "id": 65,
    "first_name": "Carsten",
    "last_name": null,
    "species": "Human",
    "age": null,
    "height": null,
    "residence": "Orvud District",
    "status": "Alive",
    "alias": null
  },
  {
    "id": 66,
    "first_name": "Phil",
    "last_name": null,
    "species": "Human",
    "age": null,
    "height": null,
    "residence": "Wall Rose",
    "status": "Unknown",
    "alias": null
  },
  {
    "id": 67,
    "first_name": "Hugo",
    "last_name": null,
    "species": "Human",
    "age": null,
    "height": null,
    "residence": "Shiganshina District",
    "status": "Unknown",
    "alias": null
  },
  {
    "id": 68,
    "first_name": "Hannes",
    "last_name": null,
    "species": "Human",
    "age": null,
    "height": null,
    "residence": "Wall Rose",
    "status": "Deceased",
    "alias": null
  },
  {
    "id": 69,
    "first_name": "Ian",
    "last_name": "Dietrich",
    "species": "Human",
    "age": null,
    "height": null,
    "residence": "Trost District",
    "status": "Deceased",
    "alias": null
  },
  {
    "id": 70,
    "first_name": "Mitabi",
    "last_name": "Jarnach",
    "species": "Human",
    "age": null,
    "height": null,
    "residence": "Trost District",
    "status": "Deceased",
    "alias": null
  },
  {
    "id": 71,
    "first_name": "Keith",
    "last_name": "Sadies",
    "species": "Human",
    "age": null,
    "height": null,
    "residence": "Wall Rose",
    "status": "Alive",
    "alias": null
  },
  {
    "id": 72,
    "first_name": "Hanna",
    "last_name": "Diament",
    "species": "Human",
    "age": null,
    "height": null,
    "residence": "Wall Rose",
    "status": "Unknown",
    "alias": null
  },
  {
    "id": 73,
    "first_name": "Ruth",
    "last_name": "Kline",
    "species": "Human",
    "age": null,
    "height": null,
    "residence": "Wall Rose",
    "status": "Deceased",
    "alias": null
  },
  {
    "id": 74,
    "first_name": "Marco",
    "last_name": "Bodt",
    "species": "Human",
    "age": 16,
    "height": null,
    "residence": "Wall Rose",
    "status": "Deceased",
    "alias": null
  },
  {
    "id": 75,
    "first_name": "Tom",
    "last_name": null,
    "species": "Human",
    "age": null,
    "height": null,
    "residence": "Wall Rose",
    "status": "Deceased",
    "alias": null
  },
  {
    "id": 76,
    "first_name": "Franz",
    "last_name": "Kefka",
    "species": "Human",
    "age": null,
    "height": null,
    "residence": "Wall Rose",
    "status": "Deceased",
    "alias": null
  },
  {
    "id": 77,
    "first_name": "Mina",
    "last_name": "Carolina",
    "species": "Human",
    "age": null,
    "height": null,
    "residence": "Wall Rose",
    "status": "Deceased",
    "alias": null
  },
  {
    "id": 78,
    "first_name": "Milieus",
    "last_name": "Zeremski",
    "species": "Human",
    "age": null,
    "height": null,
    "residence": "Wall Rose",
    "status": "Deceased",
    "alias": null
  },
  {
    "id": 79,
    "first_name": "Nack",
    "last_name": "Tierce",
    "species": "Human",
    "age": null,
    "height": null,
    "residence": "Wall Rose",
    "status": "Deceased",
    "alias": null
  },
  {
    "id": 80,
    "first_name": "Thomas",
    "last_name": "Wagner",
    "species": "Human",
    "age": null,
    "height": null,
    "residence": "Wall Rose",
    "status": "Deceased",
    "alias": null
  },
  {
    "id": 81,
    "first_name": "Theo",
    "last_name": "Magath",
    "species": "Male",
    "age": null,
    "height": null,
    "residence": "Marley",
    "status": "Alive",
    "alias": null
  },
  {
    "id": 82,
    "first_name": "Koslow",
    "last_name": null,
    "species": "Human",
    "age": null,
    "height": null,
    "residence": "Marley",
    "status": "Deceased",
    "alias": null
  },
  {
    "id": 83,
    "first_name": "Carlo",
    "last_name": null,
    "species": "Male",
    "age": null,
    "height": null,
    "residence": "Marley",
    "status": "Deceased",
    "alias": null
  },
  {
    "id": 84,
    "first_name": "Calvi",
    "last_name": null,
    "species": "Human",
    "age": null,
    "height": null,
    "residence": "Marley",
    "status": "Deceased",
    "alias": null
  },
  {
    "id": 85,
    "first_name": "Reiner",
    "last_name": "Braun",
    "species": "Human, Intelligent Titan",
    "age": 21,
    "height": 15,
    "residence": "Liberio",
    "status": "Alive",
    "alias": "Armored Titan, Armor"
  },
  {
    "id": 86,
    "first_name": "Pieck",
    "last_name": "Pieck",
    "species": "Human, Intelligent Titan",
    "age": null,
    "height": null,
    "residence": "Liberio",
    "status": "Alive",
    "alias": "Cart Titan, Cart, Quadruped-type"
  },
  {
    "id": 87,
    "first_name": "Porco",
    "last_name": "Galliard",
    "species": "Human, Intelligent Titan",
    "age": null,
    "height": 5,
    "residence": "Liberio",
    "status": "Alive",
    "alias": "Jaw Titan, Jaw, Pock"
  },
  {
    "id": 88,
    "first_name": "Falco",
    "last_name": "Grice",
    "species": "Human",
    "age": null,
    "height": null,
    "residence": "Liberio",
    "status": "Alive",
    "alias": "Ben"
  },
  {
    "id": 89,
    "first_name": "Colt",
    "last_name": "Grice",
    "species": "Human",
    "age": null,
    "height": null,
    "residence": "Liberio",
    "status": "Alive",
    "alias": null
  },
  {
    "id": 90,
    "first_name": "Gabi",
    "last_name": "Braun",
    "species": "Human",
    "age": null,
    "height": null,
    "residence": "Liberio",
    "status": "Alive",
    "alias": "Mia"
  },
  {
    "id": 91,
    "first_name": "Annie",
    "last_name": "Leonhart",
    "species": "Human, Intelligent Titan",
    "age": 20,
    "height": 14,
    "residence": "Wall Sina",
    "status": "Unknown",
    "alias": "Female Titan, Female"
  },
  {
    "id": 92,
    "first_name": "Udo",
    "last_name": null,
    "species": "Human",
    "age": null,
    "height": null,
    "residence": "Liberio",
    "status": "Deceased",
    "alias": null
  },
  {
    "id": 93,
    "first_name": "Zofia",
    "last_name": null,
    "species": "Human",
    "age": null,
    "height": null,
    "residence": "Liberio",
    "status": "Deceased",
    "alias": null
  },
  {
    "id": 94,
    "first_name": "Bertholdt",
    "last_name": "Hoover",
    "species": "Human, Intelligent Titan",
    "age": 16,
    "height": 60,
    "residence": "Wall Rose",
    "status": "Deceased",
    "alias": "Colossal Titan, Bertl"
  },
  {
    "id": 95,
    "first_name": "Marcel",
    "last_name": "Galliard",
    "species": "Human, Intelligent Titan",
    "age": null,
    "height": 5,
    "residence": "Liberio",
    "status": "Deceased",
    "alias": "Jaw Titan, Jaw"
  },
  {
    "id": 96,
    "first_name": "Tom",
    "last_name": "Xaver",
    "species": "Human, Intelligent Titan",
    "age": null,
    "height": null,
    "residence": "Liberio",
    "status": "Deceased",
    "alias": "Beast Titan"
  },
  {
    "id": 97,
    "first_name": "Eren",
    "last_name": "Kruger",
    "species": "Human, Intelligent Titan",
    "age": null,
    "height": 15,
    "residence": "Marley",
    "status": "Deceased",
    "alias": "Attack Titan, The Owl"
  },
  {
    "id": 98,
    "first_name": "Gross",
    "last_name": null,
    "species": "Human",
    "age": null,
    "height": null,
    "residence": "Marley",
    "status": "Deceased",
    "alias": null
  },
  {
    "id": 99,
    "first_name": "Historia",
    "last_name": "Reiss",
    "species": "Human",
    "age": 19,
    "height": null,
    "residence": "Wall Rose",
    "status": "Alive",
    "alias": "Christa Lenz, Goddess, True Queen of the Walls, Queen Historia"
  },
  {
    "id": 100,
    "first_name": "Wald",
    "last_name": null,
    "species": "Human",
    "age": null,
    "height": null,
    "residence": null,
    "status": "Alive",
    "alias": null
  },
  {
    "id": 101,
    "first_name": "Nicholas",
    "last_name": "Lovof",
    "species": "Human",
    "age": null,
    "height": null,
    "residence": "Wall Sina",
    "status": "Alive",
    "alias": null
  },
  {
    "id": 102,
    "first_name": "Rod",
    "last_name": "Reiss",
    "species": "Titan (formerly human)",
    "age": null,
    "height": 120,
    "residence": "Wall Sina",
    "status": "Deceased",
    "alias": "Lord Reiss, King of the Walls"
  },
  {
    "id": 103,
    "first_name": "Ulklin",
    "last_name": "Reiss",
    "species": "Human",
    "age": null,
    "height": null,
    "residence": "Wall Sina",
    "status": "Deceased",
    "alias": null
  },
  {
    "id": 104,
    "first_name": "Rod's",
    "last_name": "wife",
    "species": "Human",
    "age": null,
    "height": null,
    "residence": "Wall Sina",
    "status": "Deceased",
    "alias": null
  },
  {
    "id": 105,
    "first_name": "Florian",
    "last_name": "Reiss",
    "species": "Human",
    "age": 10,
    "height": null,
    "residence": "Wall Sina",
    "status": "Alive",
    "alias": null
  },
  {
    "id": 106,
    "first_name": "Abel",
    "last_name": "Reiss",
    "species": "Human",
    "age": 12,
    "height": null,
    "residence": "Wall Sina",
    "status": "Deceased",
    "alias": null
  },
  {
    "id": 107,
    "first_name": "Dirk",
    "last_name": "Reiss",
    "species": "Human",
    "age": 14,
    "height": null,
    "residence": "Wall Sina",
    "status": "Deceased",
    "alias": null
  },
  {
    "id": 108,
    "first_name": "Frieda",
    "last_name": "Reiss",
    "species": "Human, Intelligent Titan",
    "age": 18,
    "height": 13,
    "residence": "Wall Sina",
    "status": "Deceased",
    "alias": "King of the Walls, Founding Titan"
  },
  {
    "id": 109,
    "first_name": "Uri",
    "last_name": "Reiss",
    "species": "Human, Intelligent Titan",
    "age": null,
    "height": null,
    "residence": "Wall Sina",
    "status": "Deceased",
    "alias": "King of the Walls, Founding Titan"
  },
  {
    "id": 110,
    "first_name": "Rod's",
    "last_name": "father",
    "species": "Human, Intelligent Titan",
    "age": null,
    "height": null,
    "residence": "Wall Sina",
    "status": "Deceased",
    "alias": "King of the Walls, Founding Titan"
  },
  {
    "id": 111,
    "first_name": "Karl",
    "last_name": "Fritz",
    "species": "Human, Intelligent Titan",
    "age": null,
    "height": null,
    "residence": null,
    "status": "Deceased",
    "alias": "145th King, King of the Walls, Founding Titan, First Reiss King, First King, King Reiss, King Fritz"
  },
  {
    "id": 112,
    "first_name": "Fine",
    "last_name": "Tybur",
    "species": "Human",
    "age": null,
    "height": null,
    "residence": "Marley",
    "status": "Alive",
    "alias": null
  },
  {
    "id": 113,
    "first_name": "Lara",
    "last_name": "Tybur",
    "species": "Human, Intelligent Titan",
    "age": null,
    "height": 15,
    "residence": "Marley",
    "status": "Deceased",
    "alias": "War Hammer Titan"
  },
  {
    "id": 114,
    "first_name": "Willy",
    "last_name": "Tybur",
    "species": "Human",
    "age": null,
    "height": null,
    "residence": "Marley",
    "status": "Deceased",
    "alias": "Lord Tybur, King of our savior"
  },
  {
    "id": 115,
    "first_name": "Kiyomi",
    "last_name": "Azumabito",
    "species": "Human",
    "age": null,
    "height": null,
    "residence": "Hizuru",
    "status": "Alive",
    "alias": null
  },
  {
    "id": 116,
    "first_name": "Ellie",
    "last_name": null,
    "species": "Human",
    "age": null,
    "height": null,
    "residence": "Calaneth District",
    "status": "Alive",
    "alias": null
  },
  {
    "id": 117,
    "first_name": "Mr.",
    "last_name": "Rall",
    "species": "Human",
    "age": null,
    "height": null,
    "residence": "Calaneth District",
    "status": "Alive",
    "alias": null
  },
  {
    "id": 118,
    "first_name": "Stohess",
    "last_name": "Mayor",
    "species": "Male",
    "age": null,
    "height": null,
    "residence": "Stohess District",
    "status": "Alive",
    "alias": null
  },
  {
    "id": 119,
    "first_name": "Roderich",
    "last_name": "Roderich",
    "species": "Human",
    "age": null,
    "height": null,
    "residence": "Wall Sina",
    "status": "Alive",
    "alias": null
  },
  {
    "id": 120,
    "first_name": "Jean's",
    "last_name": "mother",
    "species": "Human",
    "age": null,
    "height": null,
    "residence": "Wall Rose",
    "status": "Alive",
    "alias": null
  },
  {
    "id": 121,
    "first_name": "Artur",
    "last_name": "Braus",
    "species": "Human",
    "age": null,
    "height": null,
    "residence": "Wall Rose",
    "status": "Alive",
    "alias": "Sasha's father"
  },
  {
    "id": 122,
    "first_name": "Kaya",
    "last_name": null,
    "species": "Human",
    "age": null,
    "height": null,
    "residence": "Wall Rose",
    "status": "Alive",
    "alias": null
  },
  {
    "id": 123,
    "first_name": "Ms.",
    "last_name": "Springer",
    "species": "Human",
    "age": null,
    "height": null,
    "residence": "Ragako",
    "status": "Alive",
    "alias": null
  },
  {
    "id": 124,
    "first_name": "Carly",
    "last_name": "Stratmann",
    "species": "Human",
    "age": 20,
    "height": null,
    "residence": "Stohess District",
    "status": "Alive",
    "alias": null
  },
  {
    "id": 125,
    "first_name": "Elliot",
    "last_name": "Stratmann",
    "species": "Human",
    "age": null,
    "height": null,
    "residence": "Stohess District",
    "status": "Alive",
    "alias": null
  },
  {
    "id": 126,
    "first_name": "Lou",
    "last_name": null,
    "species": "Human",
    "age": null,
    "height": null,
    "residence": "Stohess District",
    "status": "Alive",
    "alias": null
  },
  {
    "id": 127,
    "first_name": "Ralph",
    "last_name": null,
    "species": "Human",
    "age": null,
    "height": null,
    "residence": "Wall Sina",
    "status": "Alive",
    "alias": null
  },
  {
    "id": 128,
    "first_name": "Djel",
    "last_name": "Sannes",
    "species": "Male",
    "age": null,
    "height": null,
    "residence": "Wall Sina",
    "status": "Alive",
    "alias": null
  },
  {
    "id": 129,
    "first_name": "Fritz",
    "last_name": null,
    "species": "Human",
    "age": null,
    "height": null,
    "residence": "Wall Sina",
    "status": "Alive",
    "alias": null
  },
  {
    "id": 130,
    "first_name": "Aurille",
    "last_name": null,
    "species": "Human",
    "age": null,
    "height": null,
    "residence": "Wall Sina",
    "status": "Alive",
    "alias": null
  },
  {
    "id": 131,
    "first_name": "Gerald",
    "last_name": null,
    "species": "Human",
    "age": null,
    "height": null,
    "residence": "Wall Sina",
    "status": "Alive",
    "alias": null
  },
  {
    "id": 132,
    "first_name": "Deltoff",
    "last_name": null,
    "species": "Human",
    "age": null,
    "height": null,
    "residence": "Wall Sina",
    "status": "Alive",
    "alias": null
  },
  {
    "id": 133,
    "first_name": "Flegel",
    "last_name": "Reeves",
    "species": "Human",
    "age": null,
    "height": null,
    "residence": "Trost District",
    "status": "Alive",
    "alias": null
  },
  {
    "id": 134,
    "first_name": "Roy",
    "last_name": null,
    "species": "Human",
    "age": null,
    "height": null,
    "residence": "Wall Sina",
    "status": "Alive",
    "alias": null
  },
  {
    "id": 135,
    "first_name": "Peaure",
    "last_name": null,
    "species": "Human",
    "age": null,
    "height": null,
    "residence": null,
    "status": "Alive",
    "alias": null
  },
  {
    "id": 136,
    "first_name": "Nicolo",
    "last_name": null,
    "species": "Human",
    "age": null,
    "height": null,
    "residence": null,
    "status": "Alive",
    "alias": null
  },
  {
    "id": 137,
    "first_name": "Lisa",
    "last_name": "Braus",
    "species": "Human",
    "age": null,
    "height": null,
    "residence": "Wall Rose",
    "status": "Alive",
    "alias": "Sasha's mother"
  },
  {
    "id": 138,
    "first_name": "Moses'",
    "last_name": "mother",
    "species": "Human",
    "age": null,
    "height": null,
    "residence": "Shiganshina District",
    "status": "Unknown",
    "alias": null
  },
  {
    "id": 139,
    "first_name": "Mirror",
    "last_name": "Man",
    "species": "Human",
    "age": null,
    "height": null,
    "residence": null,
    "status": "Unknown",
    "alias": null
  },
  {
    "id": 140,
    "first_name": "Yan",
    "last_name": null,
    "species": "Human",
    "age": null,
    "height": null,
    "residence": "Underground",
    "status": "Unknown",
    "alias": null
  },
  {
    "id": 141,
    "first_name": "Dimo",
    "last_name": "Reeves",
    "species": "Human",
    "age": null,
    "height": null,
    "residence": "Trost District",
    "status": "Deceased",
    "alias": "Committee Member"
  },
  {
    "id": 142,
    "first_name": "Nick",
    "last_name": null,
    "species": "Human",
    "age": null,
    "height": null,
    "residence": "Wall Sina",
    "status": "Deceased",
    "alias": null
  },
  {
    "id": 143,
    "first_name": "Mr.",
    "last_name": "Springer",
    "species": "Titan (formerly human)",
    "age": null,
    "height": 3,
    "residence": " Ragako",
    "status": "Deceased",
    "alias": null
  },
  {
    "id": 144,
    "first_name": "Sunny",
    "last_name": "Springer",
    "species": "Titan (formerly human)",
    "age": null,
    "height": null,
    "residence": "Wall Rose",
    "status": "Deceased",
    "alias": null
  },
  {
    "id": 145,
    "first_name": "Martin",
    "last_name": "Springer",
    "species": "Titan (formerly human)",
    "age": null,
    "height": null,
    "residence": "Wall Rose",
    "status": "Deceased",
    "alias": null
  },
  {
    "id": 146,
    "first_name": "Wald",
    "last_name": null,
    "species": "Human",
    "age": null,
    "height": null,
    "residence": "Stohess District",
    "status": "Deceased",
    "alias": null
  },
  {
    "id": 147,
    "first_name": "Kemper",
    "last_name": "Boltz",
    "species": "Human",
    "age": null,
    "height": null,
    "residence": "Stohess District",
    "status": "Deceased",
    "alias": null
  },
  {
    "id": 148,
    "first_name": "Grandfather",
    "last_name": "Arlelt",
    "species": "Human",
    "age": null,
    "height": null,
    "residence": "Wall Rose, Wall Maria",
    "status": "Deceased",
    "alias": null
  },
  {
    "id": 149,
    "first_name": "Alma",
    "last_name": null,
    "species": "Human",
    "age": null,
    "height": null,
    "residence": "Wall Sina",
    "status": "Deceased",
    "alias": null
  },
  {
    "id": 150,
    "first_name": "Grisha",
    "last_name": "Jaeger",
    "species": "Human, Intelligent Titan",
    "age": 39,
    "height": null,
    "residence": "Shiganshina, District Liberio (former)",
    "status": "Deceased",
    "alias": "Attack Titan, Mysterious Titan, Founding Titan"
  },
  {
    "id": 151,
    "first_name": "Carla",
    "last_name": "Jaeger",
    "species": "Human",
    "age": null,
    "height": null,
    "residence": "Shiganshina District",
    "status": "Deceased",
    "alias": null
  },
  {
    "id": 152,
    "first_name": "Bandits",
    "last_name": null,
    "species": "Human",
    "age": null,
    "height": null,
    "residence": "Wall Maria",
    "status": "Deceased",
    "alias": null
  },
  {
    "id": 153,
    "first_name": "Mikasa's",
    "last_name": "mother",
    "species": "Human",
    "age": null,
    "height": null,
    "residence": "Wall Maria",
    "status": "Deceased",
    "alias": null
  },
  {
    "id": 154,
    "first_name": "Mikasa's",
    "last_name": "father",
    "species": "Human",
    "age": null,
    "height": null,
    "residence": "Wall Maria",
    "status": "Deceased",
    "alias": "Mr. Ackermann"
  },
  {
    "id": 155,
    "first_name": "Kuchel",
    "last_name": "Ackermann",
    "species": "Human",
    "age": null,
    "height": null,
    "residence": "Underground",
    "status": "Deceased",
    "alias": "Olympia"
  },
  {
    "id": 156,
    "first_name": "Kenny's",
    "last_name": "grandpa",
    "species": "Human",
    "age": null,
    "height": null,
    "residence": null,
    "status": "Deceased",
    "alias": null
  },
  {
    "id": 157,
    "first_name": "Mr.",
    "last_name": "Smith",
    "species": "Human",
    "age": null,
    "height": null,
    "residence": null,
    "status": null,
    "alias": null
  },
  {
    "id": 158,
    "first_name": "Pieck's",
    "last_name": "father",
    "species": "Human",
    "age": null,
    "height": null,
    "residence": "Liberio",
    "status": "Alive",
    "alias": null
  },
  {
    "id": 159,
    "first_name": "Reiner's",
    "last_name": "father",
    "species": "Human",
    "age": null,
    "height": null,
    "residence": "Liberio",
    "status": "Alive",
    "alias": null
  },
  {
    "id": 160,
    "first_name": "Grisha's",
    "last_name": "mother",
    "species": "Human",
    "age": null,
    "height": null,
    "residence": "Liberio",
    "status": "Unknown",
    "alias": null
  },
  {
    "id": 161,
    "first_name": "Mr.",
    "last_name": "Jaeger",
    "species": "Human",
    "age": null,
    "height": null,
    "residence": "Liberio",
    "status": "Unknown",
    "alias": "Grisha's father, Zeke's grandpa"
  },
  {
    "id": 162,
    "first_name": "Mr.",
    "last_name": "Leonhart",
    "species": "Human",
    "age": null,
    "height": null,
    "residence": null,
    "status": "Unknown",
    "alias": "Annie's father"
  },
  {
    "id": 163,
    "first_name": "Karina",
    "last_name": "Braun",
    "species": "Human",
    "age": null,
    "height": null,
    "residence": "Liberio",
    "status": "Unknown",
    "alias": null
  },
  {
    "id": 164,
    "first_name": "Ymir",
    "last_name": null,
    "species": "Human, Intelligent Titan",
    "age": 75,
    "height": 5,
    "residence": null,
    "status": "Deceased",
    "alias": "Freckles, Lady Ymir, Jaw Titan"
  },
  {
    "id": 165,
    "first_name": "Dina",
    "last_name": "Fritz",
    "species": "Titan (formerly human)",
    "age": null,
    "height": null,
    "residence": "Liberio",
    "status": "Deceased",
    "alias": null
  },
  {
    "id": 166,
    "first_name": "Comrade",
    "last_name": "D",
    "species": "Titan (formerly human)",
    "age": null,
    "height": 3,
    "residence": "Liberio",
    "status": "Deceased",
    "alias": null
  },
  {
    "id": 167,
    "first_name": "Talking",
    "last_name": "Titan",
    "species": "Titan (formerly human)",
    "age": null,
    "height": 6,
    "residence": "Marley",
    "status": "Deceased",
    "alias": "The Titan encountered by Ilse Langnar on the 34th expedition"
  },
  {
    "id": 168,
    "first_name": "Grice",
    "last_name": null,
    "species": "Human",
    "age": null,
    "height": null,
    "residence": "Liberio",
    "status": "Deceased",
    "alias": null
  },
  {
    "id": 169,
    "first_name": "Fay",
    "last_name": "Jaeger",
    "species": "Human",
    "age": 8,
    "height": null,
    "residence": "Liberio",
    "status": "Deceased",
    "alias": null
  },
  {
    "id": 170,
    "first_name": "Yelena",
    "last_name": null,
    "species": "Human",
    "age": null,
    "height": null,
    "residence": null,
    "status": "Alive",
    "alias": null
  },
  {
    "id": 171,
    "first_name": "Onyankopon",
    "last_name": null,
    "species": "Human",
    "age": null,
    "height": null,
    "residence": null,
    "status": "Alive",
    "alias": null
  },
  {
    "id": 172,
    "first_name": "Zeke",
    "last_name": "Jaeger",
    "species": "Human, Intelligent Titan",
    "age": 29,
    "height": 17,
    "residence": "Marley",
    "status": "Unknown",
    "alias": "Beast Titan, Monkey, Wonderboy, Beardo"
  },
  {
    "id": 173,
    "first_name": "Greiz",
    "last_name": null,
    "species": "Human",
    "age": null,
    "height": null,
    "residence": null,
    "status": "Deceased",
    "alias": null
  },
  {
    "id": 174,
    "first_name": "Ogweno",
    "last_name": null,
    "species": "Human",
    "age": null,
    "height": null,
    "residence": null,
    "status": "Alive",
    "alias": null
  },
  {
    "id": 175,
    "first_name": "Nambia",
    "last_name": null,
    "species": "Human",
    "age": null,
    "height": null,
    "residence": null,
    "status": "Alive",
    "alias": null
  },
  {
    "id": 176,
    "first_name": "Eren",
    "last_name": "Jaeger",
    "species": "Human, Intelligent Titan",
    "age": 19,
    "height": 15,
    "residence": "Wall Rose",
    "status": "Alive",
    "alias": "Suicidal Maniac, Titan boy, Attack Titan, Mysterious Titan, Berserk Titan, Titan being rampant, Founding Titan, Founder, Mister Kruger, Usurper, War Hammer Titan"
  },
  {
    "id": 177,
    "first_name": "Samuel",
    "last_name": "Linke-Jackson",
    "species": "Human",
    "age": null,
    "height": null,
    "residence": "Wall Rose",
    "status": "Alive",
    "alias": null
  },
  {
    "id": 178,
    "first_name": "Louise",
    "last_name": null,
    "species": "Human",
    "age": null,
    "height": null,
    "residence": "Trost District",
    "status": "Alive",
    "alias": null
  },
  {
    "id": 179,
    "first_name": "Floch",
    "last_name": "Forster",
    "species": "Human",
    "age": null,
    "height": null,
    "residence": "Wall Rose",
    "status": "Alive",
    "alias": null
  },
  {
    "id": 180,
    "first_name": "Wim",
    "last_name": null,
    "species": "Human",
    "age": null,
    "height": null,
    "residence": null,
    "status": "Alive",
    "alias": null
  },
  {
    "id": 181,
    "first_name": "Holger",
    "last_name": null,
    "species": "Human",
    "age": null,
    "height": null,
    "residence": null,
    "status": "Alive",
    "alias": null
  },
  {
    "id": 182,
    "first_name": "Surma",
    "last_name": null,
    "species": "Human",
    "age": null,
    "height": null,
    "residence": null,
    "status": "Alive",
    "alias": null
  },
  {
    "id": 183,
    "first_name": "Sawney",
    "last_name": null,
    "species": "Titan",
    "age": null,
    "height": 4,
    "residence": null,
    "status": "Deceased",
    "alias": null
  },
  {
    "id": 184,
    "first_name": "Beane",
    "last_name": null,
    "species": "Titan",
    "age": null,
    "height": 7,
    "residence": null,
    "status": "Deceased",
    "alias": null
  },
  {
    "id": 185,
    "first_name": "Helos",
    "last_name": null,
    "species": "Human",
    "age": null,
    "height": null,
    "residence": "Marley",
    "status": "Deceased",
    "alias": null
  },
  {
    "id": 186,
    "first_name": "Devil of All Earth",
    "last_name": null,
    "species": "Unknown",
    "age": null,
    "height": null,
    "residence": null,
    "status": "Deceased",
    "alias": null
  },
  {
    "id": 187,
    "first_name": "Ymir",
    "last_name": "Fritz",
    "species": "Human, Intelligent Titan",
    "age": null,
    "height": null,
    "residence": null,
    "status": "Deceased",
    "alias": "Christa, Founding Titan"
  },
  {
    "id": 188,
    "first_name": "Dhalis",
    "last_name": "Zachary",
    "species": "Human",
    "age": null,
    "height": null,
    "residence": "Wall Rose",
    "status": "Deceased",
    "alias": null
  }
]